{"project":"fr.wikipedia.org","page":"Intersectionnalit\u00e9","limit":20,"top_editors":[{"rank":1,"username":"Ini\u021bi","count":41,"minor":29,"first_edit":{"id":152663429,"timestamp":20181001163326},"latest_edit":{"id":178726894,"timestamp":20210112182232}},{"rank":2,"username":"Touam","count":23,"minor":0,"first_edit":{"id":152352477,"timestamp":20180920195317},"latest_edit":{"id":198181906,"timestamp":20221028131607}},{"rank":3,"username":"Vaterigu","count":12,"minor":0,"first_edit":{"id":185414319,"timestamp":20210811142527},"latest_edit":{"id":186211761,"timestamp":20210910112854}},{"rank":4,"username":"Eunostos","count":11,"minor":1,"first_edit":{"id":68503503,"timestamp":20110816221606},"latest_edit":{"id":131514215,"timestamp":20161105000740}},{"rank":5,"username":"Necrid Master","count":9,"minor":0,"first_edit":{"id":142225219,"timestamp":20171103014149},"latest_edit":{"id":185767219,"timestamp":20210824131632}},{"rank":6,"username":"Fa suisse","count":8,"minor":2,"first_edit":{"id":172326389,"timestamp":20200625104332},"latest_edit":{"id":173095656,"timestamp":20200720155151}},{"rank":7,"username":"Polymagou","count":7,"minor":6,"first_edit":{"id":175586048,"timestamp":20201015045257},"latest_edit":{"id":185419064,"timestamp":20210811181600}},{"rank":8,"username":"JMGuyon","count":6,"minor":0,"first_edit":{"id":177974909,"timestamp":20201223221435},"latest_edit":{"id":193161322,"timestamp":20220425202039}},{"rank":9,"username":"Antoniex","count":6,"minor":0,"first_edit":{"id":137781734,"timestamp":20170530093641},"latest_edit":{"id":193161650,"timestamp":20220425203309}},{"rank":10,"username":"Pautard","count":6,"minor":6,"first_edit":{"id":154224951,"timestamp":20181124170521},"latest_edit":{"id":198549599,"timestamp":20221110134448}},{"rank":11,"username":"Ismoon","count":5,"minor":1,"first_edit":{"id":196640018,"timestamp":20220902132119},"latest_edit":{"id":196641102,"timestamp":20220902140312}},{"rank":12,"username":"Tyseria","count":5,"minor":2,"first_edit":{"id":161459327,"timestamp":20190801140701},"latest_edit":{"id":189356919,"timestamp":20211230102124}},{"rank":13,"username":"Guise","count":5,"minor":0,"first_edit":{"id":161866652,"timestamp":20190816113033},"latest_edit":{"id":163184123,"timestamp":20191002131703}},{"rank":14,"username":"Braveheidi","count":5,"minor":1,"first_edit":{"id":141917979,"timestamp":20171025190923},"latest_edit":{"id":152653372,"timestamp":20181001111504}},{"rank":15,"username":"2A02:A03F:42C6:2B00:C001:6421:58FB:6748","count":4,"minor":0,"first_edit":{"id":158596966,"timestamp":20190420080816},"latest_edit":{"id":158597234,"timestamp":20190420082422}},{"rank":16,"username":"OrlodrimBot","count":4,"minor":4,"first_edit":{"id":160137566,"timestamp":20190614193809},"latest_edit":{"id":190731070,"timestamp":20220210234517}},{"rank":17,"username":"Celette","count":4,"minor":3,"first_edit":{"id":142257522,"timestamp":20171103230110},"latest_edit":{"id":158602973,"timestamp":20190420132504}},{"rank":18,"username":".Anja.","count":4,"minor":2,"first_edit":{"id":134946067,"timestamp":20170227222028},"latest_edit":{"id":185615273,"timestamp":20210819074727}},{"rank":19,"username":"Raresvent","count":4,"minor":0,"first_edit":{"id":176919518,"timestamp":20201124064646},"latest_edit":{"id":176919552,"timestamp":20201124065101}},{"rank":20,"username":"Pierre-Alain Gouanvic","count":4,"minor":1,"first_edit":{"id":87588527,"timestamp":20130113092552},"latest_edit":{"id":93750595,"timestamp":20130604040345}}],"elapsed_time":0.141}