{"project":"fr.wikipedia.org","page":"F\u00e9minisme","limit":20,"top_editors":[{"rank":1,"username":"Titi Sitria","count":70,"minor":43,"first_edit":{"id":2749007,"timestamp":20050718160218},"latest_edit":{"id":5713032,"timestamp":20060221225621}},{"rank":2,"username":"JLM","count":49,"minor":49,"first_edit":{"id":40403639,"timestamp":20090430152832},"latest_edit":{"id":198657509,"timestamp":20221114103100}},{"rank":3,"username":"193.253.44.217","count":49,"minor":0,"first_edit":{"id":1107778,"timestamp":20041123174021},"latest_edit":{"id":1109132,"timestamp":20041123222949}},{"rank":4,"username":"Celette","count":41,"minor":5,"first_edit":{"id":44658395,"timestamp":20090909124318},"latest_edit":{"id":163288406,"timestamp":20191006105634}},{"rank":5,"username":"Salebot","count":41,"minor":0,"first_edit":{"id":29115363,"timestamp":20080430011411},"latest_edit":{"id":198667121,"timestamp":20221114165941}},{"rank":6,"username":"Olivier Tanguy","count":38,"minor":5,"first_edit":{"id":104360542,"timestamp":20140603233813},"latest_edit":{"id":194945006,"timestamp":20220629205836}},{"rank":7,"username":"Hesoneofus","count":36,"minor":5,"first_edit":{"id":12793230,"timestamp":20061225210911},"latest_edit":{"id":19650140,"timestamp":20070812192610}},{"rank":8,"username":"Deaddisco","count":36,"minor":10,"first_edit":{"id":32395035,"timestamp":20080813102251},"latest_edit":{"id":61884184,"timestamp":20110202131049}},{"rank":9,"username":"Pierre-Alain Gouanvic","count":35,"minor":4,"first_edit":{"id":86667836,"timestamp":20121218071636},"latest_edit":{"id":88471867,"timestamp":20130206163824}},{"rank":10,"username":"TwoWings","count":33,"minor":4,"first_edit":{"id":87679702,"timestamp":20130115194020},"latest_edit":{"id":194467898,"timestamp":20220612092150}},{"rank":11,"username":"Zazouduwww","count":31,"minor":17,"first_edit":{"id":270419,"timestamp":20040222111427},"latest_edit":{"id":336173,"timestamp":20040327215409}},{"rank":12,"username":"Solveig","count":28,"minor":27,"first_edit":{"id":1072100,"timestamp":20041114061355},"latest_edit":{"id":14092081,"timestamp":20070212042332}},{"rank":13,"username":"Horowitz","count":27,"minor":14,"first_edit":{"id":5386831,"timestamp":20060203165256},"latest_edit":{"id":113729257,"timestamp":20150410210050}},{"rank":14,"username":"Ydecreux","count":22,"minor":5,"first_edit":{"id":116006557,"timestamp":20150615083049},"latest_edit":{"id":127280704,"timestamp":20160622194721}},{"rank":15,"username":"Laddo","count":22,"minor":12,"first_edit":{"id":16103995,"timestamp":20070421125916},"latest_edit":{"id":22933055,"timestamp":20071113224039}},{"rank":16,"username":"Pwet-pwet","count":20,"minor":6,"first_edit":{"id":14378098,"timestamp":20070222101551},"latest_edit":{"id":37978322,"timestamp":20090212222831}},{"rank":17,"username":"Tonnegrande","count":20,"minor":20,"first_edit":{"id":175928516,"timestamp":20201026045420},"latest_edit":{"id":175929146,"timestamp":20201026063602}},{"rank":18,"username":"Ornd","count":20,"minor":6,"first_edit":{"id":154048537,"timestamp":20181118092743},"latest_edit":{"id":164886565,"timestamp":20191126225942}},{"rank":19,"username":"Matou91","count":20,"minor":2,"first_edit":{"id":73590954,"timestamp":20111228003523},"latest_edit":{"id":111686156,"timestamp":20150209082713}},{"rank":20,"username":"Joker-x","count":19,"minor":0,"first_edit":{"id":5081945,"timestamp":20060117232747},"latest_edit":{"id":5342082,"timestamp":20060201065915}}],"elapsed_time":0.192}