{"project":"fr.wikipedia.org","page":"Sexisme dans la science moderne","limit":20,"top_editors":[{"rank":1,"username":"JMGuyon","count":136,"minor":0,"first_edit":{"id":177485274,"timestamp":20201210190312},"latest_edit":{"id":190878867,"timestamp":20220215225928}},{"rank":2,"username":"OrlodrimBot","count":5,"minor":5,"first_edit":{"id":178201209,"timestamp":20201230074704},"latest_edit":{"id":195286655,"timestamp":20220713105408}},{"rank":3,"username":"Pa2chant.bis","count":4,"minor":2,"first_edit":{"id":190883703,"timestamp":20220216062724},"latest_edit":{"id":193099668,"timestamp":20220423160610}},{"rank":4,"username":"Fichel Moucault","count":4,"minor":1,"first_edit":{"id":177738746,"timestamp":20201217175029},"latest_edit":{"id":177740513,"timestamp":20201217184130}},{"rank":5,"username":"Thontep","count":3,"minor":2,"first_edit":{"id":190831695,"timestamp":20220214132011},"latest_edit":{"id":190866964,"timestamp":20220215154156}},{"rank":6,"username":"RG067","count":2,"minor":2,"first_edit":{"id":177687220,"timestamp":20201216073740},"latest_edit":{"id":178057092,"timestamp":20201226100203}},{"rank":7,"username":"AwkwardChester","count":2,"minor":1,"first_edit":{"id":178035521,"timestamp":20201225190328},"latest_edit":{"id":178035660,"timestamp":20201225190736}},{"rank":8,"username":"Lomita","count":2,"minor":2,"first_edit":{"id":177515647,"timestamp":20201211152128},"latest_edit":{"id":182277677,"timestamp":20210425151234}},{"rank":9,"username":"Voivod","count":1,"minor":1,"first_edit":{"id":179042559,"timestamp":20210121064629},"latest_edit":{"id":179042559,"timestamp":20210121064629}},{"rank":10,"username":"Gemini1980","count":1,"minor":1,"first_edit":{"id":198921205,"timestamp":20221123182854},"latest_edit":{"id":198921205,"timestamp":20221123182854}},{"rank":11,"username":"194.199.3.13","count":1,"minor":0,"first_edit":{"id":197454539,"timestamp":20221003131828},"latest_edit":{"id":197454539,"timestamp":20221003131828}},{"rank":12,"username":".Anja.","count":1,"minor":1,"first_edit":{"id":186954692,"timestamp":20211007130518},"latest_edit":{"id":186954692,"timestamp":20211007130518}},{"rank":13,"username":"Pautard","count":1,"minor":1,"first_edit":{"id":180335967,"timestamp":20210226124227},"latest_edit":{"id":180335967,"timestamp":20210226124227}},{"rank":14,"username":"Milyon","count":1,"minor":1,"first_edit":{"id":190771803,"timestamp":20220212133244},"latest_edit":{"id":190771803,"timestamp":20220212133244}},{"rank":15,"username":"RobokoBot","count":1,"minor":1,"first_edit":{"id":177680659,"timestamp":20201215234341},"latest_edit":{"id":177680659,"timestamp":20201215234341}},{"rank":16,"username":"92.94.111.7","count":1,"minor":0,"first_edit":{"id":182209332,"timestamp":20210423135518},"latest_edit":{"id":182209332,"timestamp":20210423135518}},{"rank":17,"username":"WikiCleanerBot","count":1,"minor":1,"first_edit":{"id":177759218,"timestamp":20201218090952},"latest_edit":{"id":177759218,"timestamp":20201218090952}}],"elapsed_time":0.131}