{"project":"fr.wikipedia.org","page":"Handball","limit":20,"top_editors":[{"rank":1,"username":"LeFnake","count":112,"minor":27,"first_edit":{"id":78081215,"timestamp":20120427133843},"latest_edit":{"id":197352183,"timestamp":20220929161133}},{"rank":2,"username":"Ziron","count":99,"minor":0,"first_edit":{"id":46543908,"timestamp":20091106214520},"latest_edit":{"id":193833415,"timestamp":20220520083501}},{"rank":3,"username":"Salebot","count":70,"minor":0,"first_edit":{"id":26065742,"timestamp":20080211192632},"latest_edit":{"id":180694690,"timestamp":20210309084239}},{"rank":4,"username":"Clio64","count":59,"minor":33,"first_edit":{"id":1417034,"timestamp":20050203005138},"latest_edit":{"id":62470579,"timestamp":20110220020955}},{"rank":5,"username":"Flouwen","count":35,"minor":35,"first_edit":{"id":101949210,"timestamp":20140310163005},"latest_edit":{"id":153639543,"timestamp":20181103150102}},{"rank":6,"username":"Lucio fr","count":31,"minor":2,"first_edit":{"id":83747913,"timestamp":20121005130143},"latest_edit":{"id":197938787,"timestamp":20221019153419}},{"rank":7,"username":"Guillaume.francois55","count":26,"minor":13,"first_edit":{"id":7316708,"timestamp":20060516155011},"latest_edit":{"id":40791189,"timestamp":20090512111004}},{"rank":8,"username":"HaricotBleu","count":25,"minor":0,"first_edit":{"id":12770681,"timestamp":20061224131355},"latest_edit":{"id":38721859,"timestamp":20090307173728}},{"rank":9,"username":"JLM","count":17,"minor":17,"first_edit":{"id":70855724,"timestamp":20111008102406},"latest_edit":{"id":183099488,"timestamp":20210520214634}},{"rank":10,"username":"PetitCanard","count":16,"minor":2,"first_edit":{"id":68307300,"timestamp":20110810224813},"latest_edit":{"id":117318543,"timestamp":20150730131730}},{"rank":11,"username":"Do not follow","count":15,"minor":14,"first_edit":{"id":132000786,"timestamp":20161121133426},"latest_edit":{"id":189338562,"timestamp":20211229190947}},{"rank":12,"username":"Teuxe","count":14,"minor":9,"first_edit":{"id":35507942,"timestamp":20081122220459},"latest_edit":{"id":35511976,"timestamp":20081123020834}},{"rank":13,"username":"Sebleouf","count":10,"minor":10,"first_edit":{"id":90127604,"timestamp":20130314133341},"latest_edit":{"id":192753339,"timestamp":20220410154644}},{"rank":14,"username":"195.93.102.37","count":10,"minor":0,"first_edit":{"id":5808293,"timestamp":20060227204650},"latest_edit":{"id":7973130,"timestamp":20060615140034}},{"rank":15,"username":"DocteurCosmos","count":9,"minor":4,"first_edit":{"id":15835811,"timestamp":20070412075007},"latest_edit":{"id":103572545,"timestamp":20140506132023}},{"rank":16,"username":"BerAnth","count":9,"minor":1,"first_edit":{"id":110005413,"timestamp":20141216143343},"latest_edit":{"id":159872904,"timestamp":20190605091053}},{"rank":17,"username":"WikiCleanerBot","count":8,"minor":8,"first_edit":{"id":107338454,"timestamp":20140911060356},"latest_edit":{"id":197688344,"timestamp":20221012094210}},{"rank":18,"username":"Ubisport","count":8,"minor":0,"first_edit":{"id":29310253,"timestamp":20080506104206},"latest_edit":{"id":29315265,"timestamp":20080506133351}},{"rank":19,"username":"Arcyon37","count":8,"minor":8,"first_edit":{"id":132315806,"timestamp":20161201190401},"latest_edit":{"id":187460687,"timestamp":20211026171917}},{"rank":20,"username":"88.168.130.182","count":7,"minor":0,"first_edit":{"id":49569056,"timestamp":20100203134150},"latest_edit":{"id":76456130,"timestamp":20120308164227}}],"elapsed_time":0.191}